{"pageContext":{"group":[{"node":{"fields":{"slug":"/posts/about-2016"},"html":"<p><img src=\"https://zerosoul.github.io/2015/12/20/about-2016/about-2016.jpg\" alt=\"carrying man\"></p>\n<h1 id=\"楔子\"><a href=\"#%E6%A5%94%E5%AD%90\" aria-hidden=\"true\" class=\"anchor\"><svg aria-hidden=\"true\" height=\"16\" version=\"1.1\" viewBox=\"0 0 16 16\" width=\"16\"><path fill-rule=\"evenodd\" d=\"M4 9h1v1H4c-1.5 0-3-1.69-3-3.5S2.55 3 4 3h4c1.45 0 3 1.69 3 3.5 0 1.41-.91 2.72-2 3.25V8.59c.58-.45 1-1.27 1-2.09C10 5.22 8.98 4 8 4H4c-.98 0-2 1.22-2 2.5S3 9 4 9zm9-3h-1v1h1c1 0 2 1.22 2 2.5S13.98 12 13 12H9c-.98 0-2-1.22-2-2.5 0-.83.42-1.64 1-2.09V6.25c-1.09.53-2 1.84-2 3.25C6 11.31 7.55 13 9 13h4c1.45 0 3-1.69 3-3.5S14.5 6 13 6z\"></path></svg></a>楔子</h1>\n<p>生命是场持续而长久的积累，没有人真正在乎你在何时，在何地，是在烧着脑细胞，还是在洒着汗水。人们往往只是在你惊艳众人那一刻惊呼：卧槽，这么牛X怎么做到的？！甚至没有仔细听你解释是如何做到的，就去猎奇下一个惊艳时刻。所以，没那么多观众，放轻松，别活得太累。偶尔遇到愿意听你说到口干舌燥的，别犹豫，那不是友情便是爱情。</p>\n<h1 id=\"正文\"><a href=\"#%E6%AD%A3%E6%96%87\" aria-hidden=\"true\" class=\"anchor\"><svg aria-hidden=\"true\" height=\"16\" version=\"1.1\" viewBox=\"0 0 16 16\" width=\"16\"><path fill-rule=\"evenodd\" d=\"M4 9h1v1H4c-1.5 0-3-1.69-3-3.5S2.55 3 4 3h4c1.45 0 3 1.69 3 3.5 0 1.41-.91 2.72-2 3.25V8.59c.58-.45 1-1.27 1-2.09C10 5.22 8.98 4 8 4H4c-.98 0-2 1.22-2 2.5S3 9 4 9zm9-3h-1v1h1c1 0 2 1.22 2 2.5S13.98 12 13 12H9c-.98 0-2-1.22-2-2.5 0-.83.42-1.64 1-2.09V6.25c-1.09.53-2 1.84-2 3.25C6 11.31 7.55 13 9 13h4c1.45 0 3-1.69 3-3.5S14.5 6 13 6z\"></path></svg></a>正文</h1>\n<p>去年此时，我大概在构思今年要做的事情，并有意地把其中<a href=\"https://zerosoul.github.io/2015/02/01/against-the-flow/\">十件事</a>以博文的形式暴露出来，其目的是为了形成某种监督，进而对自己有所激励。此时此刻，恰好一年，这种方式目前来看是有效果的，所以没有理由不沿用一下。</p>\n<ol>\n<li>\n<p>每月写博文<br>\n忙碌不是逃避思考的借口，恰恰是应该坐下来想一下：为什么这么忙？以前常常有想法，却没有以文字的方式沉淀下来，我觉得是种浪费，效率上的浪费，因为能把思考写出来才有生根发芽的可能性，好记性不如烂博文。一篇技术，一点译文，一篇随笔，或者读书笔记都行，每月至少两篇吧。一年下来24篇，恩，不能再少了。</p>\n</li>\n<li>\n<p>物尽其用<br>\n这里的“物”，主要指的是我的MAC本。MAC除了用来装X，对于开发人员更重要的是提高效率，目前我还没有完全适应使用MAC工作，所以物尽其用还有距离呢。当然，工具终究是工具，更重要的是想法，两条腿走路，更稳当一些。</p>\n</li>\n<li>\n<p>APP<br>\n在技术行业工作了几年，耳濡目染久了，也有了互联网产品情节。所以想凭一己之力做个能解决个人具体需求的APP产品，由于自己是干前端的，自然而然的就想到了以前端方式来做。这个过程应该是个学习与实践的好机会，恩，好好玩。</p>\n</li>\n<li>\n<p>塑身<br>\n今年跑步坚持的还不错，身材也相应地变好了一些，但距离“好身材”还略远。所以借着今年打下的底子，继续坚持跑步的同时，办个健身卡，有条件就再请个私教，制定科学的健身计划，持之以恒。虽然走的是健身流程，但最终目的还是想打造完美的身材协调比例，比如肩膀匀不匀称，小腿粗不粗壮，挺胸抬头，全身看上去很协调，就算OK。总之，“主要看气质”，这也是我用的是“塑身”一词，而不是“健身”的原因，至于胸肌，腹肌，肱二头肌发不发达，恩，全是赠品。</p>\n</li>\n<li>\n<p>环台湾岛骑行<br>\n本来计划在今年春节期间去，种种原因拖延到现在，已经来不及了，推到下一年年底吧。或许还是一个人，或许是两人，恩，不能再多了…</p>\n</li>\n<li>\n<p>阅读<br>\n听说能让人保持创造力的最好方式便是持续地阅读，如果说今年的阅读是为了广度，那么明年便是着重深度。不求多，但求精，速度不快，一两个月啃下一本足矣，附带读书笔记。So… 10本书吧，不能再多了，再多就醉了。</p>\n</li>\n<li>\n<p>再去一次怀化某山村<br>\n今年10月份去了次，山清水秀，民风淳朴，与那里结下了更为深厚的不解之缘。从今年开始，每年都会去一次。</p>\n</li>\n<li>\n<p>英语进阶<br>\n英语一直是半瓶子醋水平，虽说应付工作日常足矣，但作为一种开阔视野的好工具，谁不想更为全面地掌握呢。打算通过翻译一本书做起，也算是给“阅读”和“博文”做贡献。</p>\n</li>\n<li>\n<p>摄影进阶<br>\n摄影是个烧钱的爱好，我不是器材党，所以目前来看，总投资没超过5K，都不好意思说自己喜欢摄影了。所谓的进阶，可能更多的是片子的后期。另，入手一个广角镜头，恩，不能再多了。</p>\n</li>\n<li>\n<p>学一种乐器<br>\n说来惭愧，曾经有学吉他的冲动，但也就止于冲动了。吉他携带有些不方便，我更习惯低调，所以想到了口琴，恩，练练口活。</p>\n</li>\n</ol>\n<p>还是那个意思：10件事不是目标，也不是梦想，只是10件事。有些需要常做，比如塑身，有些是一次性，比如骑行，有些烧脑，有些烧钱，有些流汗，甚至有些流泪。不管怎样，都需要努力。努力不是一场真人秀，更像是在做幕后，在看不到的时间与空间持续付出着…</p>\n<p>至于梦想，我觉得其实是一个很平常的东西，那句话怎么说的来着：梦想就像内裤，你得有，但是不要经常拿出来炫耀。从不觉得一个人为了梦想付出很多就显得很高尚。每个人都有自己的生活方式，没有梦想或者不愿意为梦想付出的人也值得尊重，毕竟做成一件事有时不是靠实力，还有运气。</p>\n<p>“内裤”就不晒了，不过做完以上10件事，梦想应该是更近了一步，更何况明年不止这10件。</p>\n<p>努力成为自己想成为的人，不明不白盲目努力的生活，不值得一过。</p>","frontmatter":{"title":"杨二小","date":"2015-12-20T09:31:37.000Z","category":"技术","tags":["年终总结","计划"],"cover":"https://zerosoul.github.io/2015/12/20/about-2016/about-2016.jpg"},"tableOfContents":"<ul>\n<li><a href=\"/posts/about-2016/#%E6%A5%94%E5%AD%90\">楔子</a></li>\n<li><a href=\"/posts/about-2016/#%E6%AD%A3%E6%96%87\">正文</a></li>\n</ul>","excerpt":"楔子 生命是场持续而长久的积累，没有人真正在乎你在何时，在何地，是在烧着脑细胞，还是在洒着汗水。人们往往只是在你惊艳众人那一刻惊呼：卧槽，这么牛X…"}},{"node":{"fields":{"slug":"/posts/against-the-flow"},"html":"<p><img src=\"https://zerosoul.github.io/2015/02/01/against-the-flow/against_the_flow.jpg\" alt=\"running boy\"></p>\n<h1 id=\"一\"><a href=\"#%E4%B8%80\" aria-hidden=\"true\" class=\"anchor\"><svg aria-hidden=\"true\" height=\"16\" version=\"1.1\" viewBox=\"0 0 16 16\" width=\"16\"><path fill-rule=\"evenodd\" d=\"M4 9h1v1H4c-1.5 0-3-1.69-3-3.5S2.55 3 4 3h4c1.45 0 3 1.69 3 3.5 0 1.41-.91 2.72-2 3.25V8.59c.58-.45 1-1.27 1-2.09C10 5.22 8.98 4 8 4H4c-.98 0-2 1.22-2 2.5S3 9 4 9zm9-3h-1v1h1c1 0 2 1.22 2 2.5S13.98 12 13 12H9c-.98 0-2-1.22-2-2.5 0-.83.42-1.64 1-2.09V6.25c-1.09.53-2 1.84-2 3.25C6 11.31 7.55 13 9 13h4c1.45 0 3-1.69 3-3.5S14.5 6 13 6z\"></path></svg></a>(一)</h1>\n<p>当在公司年会听到视频里的自己说出“累”字时，虽然早有心理准备，心里还是咯噔了一下。2014年，你累吗？说不累是假的，从公司的第一个前端做起，现在发展到四人，期间的酸甜苦辣自己最清楚。从单打独斗，习惯了所有问题一个人搞定，到任务的分配，人力的安排，搞定自己那一块的同时还得随时协调其它部门的问题。好在前端个个都是有节操，不，有职业素养的人，后来的许多事，一个眼神的交流就够了，基情，不，激情就是这么来的，累也值了。</p>\n<h1 id=\"二\"><a href=\"#%E4%BA%8C\" aria-hidden=\"true\" class=\"anchor\"><svg aria-hidden=\"true\" height=\"16\" version=\"1.1\" viewBox=\"0 0 16 16\" width=\"16\"><path fill-rule=\"evenodd\" d=\"M4 9h1v1H4c-1.5 0-3-1.69-3-3.5S2.55 3 4 3h4c1.45 0 3 1.69 3 3.5 0 1.41-.91 2.72-2 3.25V8.59c.58-.45 1-1.27 1-2.09C10 5.22 8.98 4 8 4H4c-.98 0-2 1.22-2 2.5S3 9 4 9zm9-3h-1v1h1c1 0 2 1.22 2 2.5S13.98 12 13 12H9c-.98 0-2-1.22-2-2.5 0-.83.42-1.64 1-2.09V6.25c-1.09.53-2 1.84-2 3.25C6 11.31 7.55 13 9 13h4c1.45 0 3-1.69 3-3.5S14.5 6 13 6z\"></path></svg></a>(二)</h1>\n<p>这一年过得好快，几乎是一路狂奔，每天都在解决问题，到头来却把自己的问题一直拖到了现在。2014年，我变成了一个无趣的人，给不了别人快乐与幸福，只好把闷骚投入到工作中。2015年，我想改变，波折肯定有的，就像心电图，那表明自己还活着。想了想，新的一年想做的大概有这么几件事：</p>\n<ol>\n<li>打铁还需自身硬，所以第一件事就是健身。似乎是个老生常谈了，但身体这事儿，就像防火，等到出问题时就晚了。健身的方式很简单，爬楼梯[17层]和跑步，爬楼已经坚持大概四个月了，每个工作日两次，所以只需重启跑步。</li>\n<li>阅读。似乎也是个老生常谈，但阅读这事儿，得细水长流。2014年，新增了43本书，其中已读大概占三分之二，剩下的滚到2015年，加之新计划入手的11本书，够够的。</li>\n<li>一天一个苹果。</li>\n<li>去掉黑眼角，听说提高睡眠质量是根本，而谈质量心态平和是根本，所以还是得“随缘向善，阿弥陀佛”。</li>\n<li>给父母，奶奶健康体检</li>\n<li>带父母来北京看看，圆母亲天安门前留影的愿望</li>\n<li>在家买套房，让家人过个安全省事的暖冬。父母为我操劳一辈子，有时想想为他们做的真的很少。我就是一风筝，飘得再远，也是有根线牵着，线的那头，便是家。</li>\n<li>练练口才，不再闷骚。多去参加一些前端活动，或许管用。</li>\n<li>戒酒。白酒本来就不沾，从今以后啤酒也不碰了。酒，烟，小轿车和保险，这辈子和我无缘了，给别人买的不算。</li>\n<li>凑个假期，回骑行的某个地方看看。三年前的那次长途骑行发生了太多的故事，后来和一些人都有或多或少的联系，总觉得这是一份得之不易的缘分，应该回去看看，既是感恩，也是放松之旅。</li>\n</ol>\n<p>我个人一直很抵触“目标”一词，因为它让人有距离感，“事情”就不一样了，围绕在身边的感觉，任何值得做的事情都值得现在去做。所以以上都是一些2015要做或者在做的事情，不是目标。有些很简单，有些很枯燥，有些蹦一蹦还是够得到。当然，一年很长，不会就做这些事，有些事没必要列出来，之所以说出上面那些，是为了形成某种监督。比如某天你见到我，问最近在看什么书，如果我回答得支支吾吾的，你就可以立马断定：丫就是一骗子！再比如某日你碰到我，问今天吃苹果没，我也可以理直气壮地勒索你一个苹果。</p>\n<h1 id=\"三\"><a href=\"#%E4%B8%89\" aria-hidden=\"true\" class=\"anchor\"><svg aria-hidden=\"true\" height=\"16\" version=\"1.1\" viewBox=\"0 0 16 16\" width=\"16\"><path fill-rule=\"evenodd\" d=\"M4 9h1v1H4c-1.5 0-3-1.69-3-3.5S2.55 3 4 3h4c1.45 0 3 1.69 3 3.5 0 1.41-.91 2.72-2 3.25V8.59c.58-.45 1-1.27 1-2.09C10 5.22 8.98 4 8 4H4c-.98 0-2 1.22-2 2.5S3 9 4 9zm9-3h-1v1h1c1 0 2 1.22 2 2.5S13.98 12 13 12H9c-.98 0-2-1.22-2-2.5 0-.83.42-1.64 1-2.09V6.25c-1.09.53-2 1.84-2 3.25C6 11.31 7.55 13 9 13h4c1.45 0 3-1.69 3-3.5S14.5 6 13 6z\"></path></svg></a>(三)</h1>\n<blockquote>\n<p>如果生活的本意是将一个人当做一件产品来打磨的话，当前的自己只能是件半成品。我不想最终变成残次品，所以，还得继续接受生活的敲打。</p>\n</blockquote>\n<p>杨二离开了，逆流鱼又来了，意味着新的一年，不能再顺着自己了。给一些期许吧：<strong>生活复杂，自我简单，标新立异，化繁为简。</strong></p>\n<h1 id=\"后记\"><a href=\"#%E5%90%8E%E8%AE%B0\" aria-hidden=\"true\" class=\"anchor\"><svg aria-hidden=\"true\" height=\"16\" version=\"1.1\" viewBox=\"0 0 16 16\" width=\"16\"><path fill-rule=\"evenodd\" d=\"M4 9h1v1H4c-1.5 0-3-1.69-3-3.5S2.55 3 4 3h4c1.45 0 3 1.69 3 3.5 0 1.41-.91 2.72-2 3.25V8.59c.58-.45 1-1.27 1-2.09C10 5.22 8.98 4 8 4H4c-.98 0-2 1.22-2 2.5S3 9 4 9zm9-3h-1v1h1c1 0 2 1.22 2 2.5S13.98 12 13 12H9c-.98 0-2-1.22-2-2.5 0-.83.42-1.64 1-2.09V6.25c-1.09.53-2 1.84-2 3.25C6 11.31 7.55 13 9 13h4c1.45 0 3-1.69 3-3.5S14.5 6 13 6z\"></path></svg></a>后记</h1>\n<p>一年快过去了，在2015年11月的某一天，我总结了下年初写下的这些事：把完成的或者已经养成习惯的划掉，剩下是没做或者没做完的和失败的。阅读，属于没做完的，新年之前差不多能完成；体检属于没做的，这个不算难，但是父母说没必要，天冷了，嫌麻烦，也就拖到现在了，等天气暖和了再做吧；练口才，说实话，已经放弃治疗o(╯□╰)o；戒酒，这个在年中最终还是没抵制住，喝了些啤酒，只好把底线往下拉一拉：不要喝醉。2015马上过去了，我希望能交出让自己满意的成绩单。加油吧，骚年！</p>","frontmatter":{"title":"逆流鱼","date":"2015-02-01T09:31:37.000Z","category":"随笔","tags":["计划","年终总结"],"cover":"https://zerosoul.github.io/2015/02/01/against-the-flow/against_the_flow.jpg"},"tableOfContents":"<ul>\n<li><a href=\"/posts/against-the-flow/#%E4%B8%80\">(一)</a></li>\n<li><a href=\"/posts/against-the-flow/#%E4%BA%8C\">(二)</a></li>\n<li><a href=\"/posts/against-the-flow/#%E4%B8%89\">(三)</a></li>\n<li><a href=\"/posts/against-the-flow/#%E5%90%8E%E8%AE%B0\">后记</a></li>\n</ul>","excerpt":"(一) 当在公司年会听到视频里的自己说出“累”字时，虽然早有心理准备，心里还是咯噔了一下。201…"}}],"pathPrefix":"tags/计划","first":true,"last":true,"index":1,"pageCount":1,"additionalContext":{"total":2,"tag":"计划"}}}